<UAPermission lastUpdated="" permissionArtifactId="360bd529-d66e-11ea-82b7-88d7f63df177" ttl="" txnId="f4838ff3-9273-4ad3-868e-9bb054bcccad"><Permission><Owner operatorId=""><Pilot uaplNo="" validTo=""/></Owner><FlightDetails><UADetails uinNo="1"/><FlightPurpose frequency="" shortDesc="Provisional test"/><PayloadDetails payloadDetails="Not specified" payloadWeight="Not specified"/><FlightParameters flightEndTime="2020-08-04T22:40:45.806157+05:30" flightStartTime="2020-08-04T21:47:45.806157+05:30" frequenciesUsed=""><Coordinates><Coordinate latitude="12.934158" longitude="77.609316"/><Coordinate latitude="12.934796" longitude="77.609852"/><Coordinate latitude="12.934183" longitude="77.610646"/><Coordinate latitude="12.933551" longitude="77.6101"/><Coordinate latitude="12.934158" longitude="77.609316"/></Coordinates></FlightParameters></FlightDetails></Permission></UAPermission>
